{
  "JMSServer": {
    "summaryAttributes": {
      "PersistentStore":  {},
      "Target": {}
    },
    "attributeDetails": {
      "BlockingSendPolicy": {
        "options": [
          { "value": "FIFO", "labelKey": "options-fifo-label" },
          { "value": "Preemptive", "labelKey": "options-preemptive-label" }
        ]
      },
      "BytesMaximum": {
        "validators": [ "range(-1,)" ]
      },
      "BytesThresholdHigh": {
        "validators": [ "range(-1,)" ]
      },
      "BytesThresholdLow": {
        "validators": [ "range(-1,)" ]
      },
      "ExpirationScanInterval": {
        "validators": [ "range(0,)" ]
      },
      "MaximumMessageSize": {
        "validators": [ "range(0,)" ]
      },
      "MessageBufferSize": {
        "validators": [ "range(-1,)" ]
      },
      "MessageCompressionOptions": {
        "options": [
          { "value": "GZIP_DEFAULT_COMPRESSION", "labelKey":  "jms-message-compression-default-label" },
          { "value": "GZIP_BEST_COMPRESSION", "labelKey":  "jms-message-compression-best-compression-label" },
          { "value": "GZIP_BEST_SPEED", "labelKey":  "jms-message-compression-fastest-compression-label" },
          { "value": "LZF", "labelKey":  "jms-message-compression-lzf-label" }
        ]
      },
      "MessagesMaximum": {
        "validators": [ "range(-1,)" ]
      },
      "MessagesThresholdHigh": {
        "validators": [ "range(-1,)" ]
      },
      "MessagesThresholdLow": {
        "validators": [ "range(-1,)" ]
      },
      "PagingBlockSize": {
        "validators": [ "range(-1,8192)" ]
      },
      "PagingIoBufferSize": {
        "validators": [ "range(-1,67108864)" ]
      },
      "PagingMaxFileSize": {
        "validators": [ "range(10485760,)" ]
      },
      "PagingMaxWindowBufferSize": {
        "validators": [ "range(-1,1073741824)" ]
      },
      "PagingMinWindowBufferSize": {
        "validators": [ "range(-1,1073741824)" ]
      }
    },
    "sections": [
      {
        "type": "tab",
        "labelKey": "general-tab-label",
        "sections": [
          {
            "type": "attributes",
            "attributes": [
              "StoreEnabled",
              "AllowsPersistentDowngrade",
              "PersistentStore",
              "MessageBufferSize",
              "ExpirationScanInterval",
              "HostingTemporaryDestinations",
              "TemporaryTemplateResource",
              "TemporaryTemplateName",
              "DeploymentOrder",
              "Notes",
              "Target"
            ]
          },
          {
            "type": "attributesCollapsible",
            "labelKey": "advanced-label",
            "attributes": [
              "JDBCStoreUpgradeEnabled",
              "StoreMessageCompressionEnabled",
              "MessageCompressionOptions",
              "InsertionPausedAtStartup",
              "ProductionPausedAtStartup",
              "ConsumptionPausedAtStartup"
            ],
            "addRemainingAttributes": true
          }
        ]
      },
      {
        "type": "attributesTab",
        "labelKey": "thresholds-tab-label",
        "attributes": [
          "BlockingSendPolicy",
          "MaximumMessageSize",
          "BytesThresholdLow",
          "MessagesThresholdLow",
          "BytesThresholdHigh",
          "MessagesThresholdHigh",
          "BytesMaximum",
          "MessagesMaximum"
        ]
      },
      {
        "type": "attributesTab",
        "labelKey": "paging-configuration-tab-label",
        "attributes": [
          "PagingFileLockingEnabled",
          "PagingMessageCompressionEnabled",
          "PagingDirectory",
          "PagingMinWindowBufferSize",
          "PagingMaxWindowBufferSize",
          "PagingMaxFileSize",
          "PagingBlockSize",
          "PagingIoBufferSize"
        ]
      },
      {
        "type": "folderTab",
        "folder": "JmsMessageLogFile"
      },
      {
        "type": "hidden",
        "folders": [
          "JmsSessionPool"
        ],
        "attributes": [
          "BytesPagingEnabled",
          "MessageCompressionOptionsOverride",
          "MessagesPagingEnabled"
        ]
      }
    ]
  },
  "JMSServer/JmsMessageLogFile": {
    "attributeDetails": {
      "BufferSizeKb": {
        "validators": [ "range(0,)" ]
      },
      "FileCount": {
        "validators": [ "range(1,99999)" ]
      },
      "FileMinSize": {
        "disabled": "jmsMessageLogRotateSizeFields",
        "validators": [ "range(1,2097150)" ]
      },
      "FileTimeSpan": {
        "disabled": "jmsMessageLogRotateTimeFields",
        "validators": [ "range(1,)" ]
      },
      "FileTimeSpanFactor": {
        "disabled": "jmsMessageLogRotateTimeFields",
        "validators": [ "range(0,)" ]
      },
      "RotationTime": {
        "disabled": "jmsMessageLogRotateTimeFields"
      },
      "RotationType": {
        "options": [
          { "value": "bySize", "labelKey": "options-by-size-label" },
          { "value": "byTime", "labelKey":  "options-by-time-label" },
          { "value": "none", "labelKey":  "options-none-label" },
          { "value": "bySizeOrTime", "labelKey":  "options-by-size-or-time-label" }
        ]
      }
    },
    "sections": [
      {
        "type": "attributes",
        "attributes": [
          "FileName",
          "RotationType",
          "RotateLogOnStartup",
          "NumberOfFilesLimited",
          "FileMinSize",
          "RotationTime",
          "FileTimeSpan",
          "FileTimeSpanFactor",
          "FileCount",
          "LogFileRotationDir",
          "BufferSizeKb",
          "DateFormatPattern",
          "Notes"
        ]
      },
      {
        "type": "attributesCollapsible",
        "labelKey": "advanced-label",
        "addRemainingAttributes": true
      }
    ]
  }
}