{
  "SystemComponent": {
    "summaryAttributes": {
      "ComponentType": {},
      "Machine": {}
    },
    "attributeDetails": {
      "Machine": {
        "editorType": "combo",
        "optionsMethod": "getMachineOptions"
      },
      "NMSocketCreateTimeoutInMillis": {
        "validators": [ "range(0,)" ]
      },
      "RestartDelaySeconds": {
        "validators": [ "range(0,)" ]
      },
      "RestartIntervalSeconds": {
        "validators": [ "range(300,)" ]
      },
      "RestartMax": {
        "validators": [ "range(0,)" ]
      }
    },
    "sections": [
      {
        "type": "tab",
        "labelKey": "general-tab-label",
        "sections": [
          {
            "type": "attributes",
            "attributes": [
              "ComponentType",
              "Machine",
              "AutoRestart",
              "RestartDelaySeconds",
              "RestartIntervalSeconds",
              "RestartMax",
              "NMSocketCreateTimeoutInMillis",
              "Notes"
            ]
          },
          {
            "type": "attributesCollapsible",
            "labelKey": "advanced-label",
            "addRemainingAttributes": true
          }
        ]
      },
      {
        "type": "folderTab",
        "folder": "SystemComponentStart"
      }
    ]
  },
  "SystemComponent/SystemComponentStart": {
    "attributeDetails": {
      "Arguments": {
        "delimiter": " "
      },
      "ClassPath": {
        "archiveTypes": ["classpathLibrary"]
      },
      "JavaHome": {
        "fileOptions": [{"type": "dir"}]
      },
      "MwHome": {
        "fileOptions": [{"type": "dir"}]
      },
      "RootDirectory": {
        "fileOptions": [{"type": "dir"}]
      }
    },
    "sections": [
      {
        "type": "attributes",
        "attributes": [
          "JavaHome",
          "JavaVendor",
          "MwHome",
          "RootDirectory",
          "ClassPath",
          "Arguments",
          "Notes"
        ]
      },
      {
        "type": "attributesCollapsible",
        "labelKey": "advanced-label",
        "addRemainingAttributes": true
      },
      {
        "type": "hidden",
        "attributes": [
          "BeaHome"
        ]
      }
    ]
  }
}