{
  "path": "topology",
  "children": [
    {
      "path": "Cluster"
    },
    {
      "path": "Machine"
    },
    {
      "path": "MigratableTarget"
    },
    {
      "path": "NMProperties"
    },
    {
      "path": "SecurityConfiguration"
    },
    {
      "path": "Server"
    },
    {
      "path": "ServerTemplate"
    },
    {
      "path": "UnixMachine"
    },
    {
      "path": "VirtualHost"
    },
    {
      "path": "WebserviceSecurity"
    },
    {
      "path": "XMLEntityCache"
    },
    {
      "path": "XMLRegistry"
    }
  ]
}
